{"device":"Design","url":"http:\/\/makeprojects.com\/Project\/World+Cultures\/1743\/1","guide":{"author":{"text":"Maya","userid":9055},"categories":["Design","Paper Crafts"],"conclusion":"","difficulty":"Moderate","documents":[],"flags":[{"title":"User-Contributed Project","flagid":"GUIDE_USER_CONTRIBUTED","text":"This project guide is not managed by MAKE staff."}],"guideid":1743,"image":{"imageid":0,"text":"http:\/\/cacher.dozuki.net\/static\/images\/make\/guide\/NoImageMP_96x72.gif"},"introduction":"<p>Whoa! I love the culture of this country. It's amazing. The people are so kind. The languages are so diverse.<\/p>","introduction_rendered":"<p>Whoa! I love the culture of this country. It's amazing. The people are so kind. The languages are so diverse.<\/p>","locale":"en","parts":[],"prereqs":[],"steps":[],"subject":"","summary":"The design of my own country. I want to persuade people to come to my country.","time_required":null,"title":"World Cultures","tools":[],"type":"technique"},"guideid":"1743"}