{"device":"Gadgets","url":"http:\/\/makeprojects.com\/Project\/Automatic+led+stairs+controller\/2201\/1","guide":{"author":{"text":"admin","userid":11383},"categories":["Gadgets","Soldering"],"conclusion":"","difficulty":"Moderate","documents":[],"flags":[{"title":"Missing Images","flagid":"GUIDE_MISSING_IMAGES","text":"This guide contains steps that are missing images."},{"title":"Missing Steps","flagid":"GUIDE_MISSING_STEPS","text":"This project guide is incomplete or missing critical steps."},{"title":"Unpublished","flagid":"GUIDE_PRIVATE","text":"This project guide will not appear in search results but can still be viewed by anyone!"},{"title":"User-Contributed Project","flagid":"GUIDE_USER_CONTRIBUTED","text":"This project guide is not managed by MAKE staff."}],"guideid":2201,"image":{"imageid":0,"text":"http:\/\/cacher.dozuki.net\/static\/images\/make\/guide\/NoImageMP_96x72.gif"},"introduction":"","introduction_rendered":"","locale":"en","parts":[],"prereqs":[],"steps":[],"subject":"","summary":"This instruction is how I assembled my Automatic Led Stairs Controller.","time_required":null,"title":"Automatic led stairs controller","tools":[],"type":"project"},"guideid":"2201"}