{"device":"Desserts","url":"http:\/\/makeprojects.com\/Project\/The+PERFECT+Chocolate+Chip+Cookie\/2462\/1","guide":{"author":{"text":"Kat Yuen","userid":13506},"categories":["Desserts"],"conclusion":"","difficulty":"Moderate","documents":[],"flags":[{"title":"User-Contributed Project","flagid":"GUIDE_USER_CONTRIBUTED","text":"This project guide is not managed by MAKE staff."}],"guideid":2462,"image":{"imageid":0,"text":"http:\/\/cacher.dozuki.net\/static\/images\/make\/guide\/NoImageMP_96x72.gif"},"introduction":"","introduction_rendered":"<div class=\"parts\"><strong>Relevant parts<\/strong><ul><li><a href=\"http:\/\/makeprojects.com\/Item\/All-purpose_flour\">All-purpose flour<\/a><\/li><li><a href=\"http:\/\/makeprojects.com\/Item\/Baking_soda\">Baking soda<\/a><\/li><li><a href=\"http:\/\/makeprojects.com\/Item\/Baking_powder\">Baking powder<\/a><\/li><\/ul><\/div><div class=\"tools\"><strong>Tools<\/strong><ul><li><a href=\"http:\/\/makeprojects.com\/Item\/2_Baking_sheets\">2 Baking sheets<\/a><\/li><li><a href=\"http:\/\/makeprojects.com\/Item\/Assorted_mixing_bowls\">Assorted mixing bowls<\/a><\/li><li><a href=\"http:\/\/makeprojects.com\/Item\/measuring_cups_and_spoons\">measuring cups and spoons<\/a><\/li><\/ul><\/div>","locale":"en","parts":[{"text":"All-purpose flour","notes":"","url":"http:\/\/makeprojects.com\/Item\/All-purpose_flour","thumbnail":""},{"text":"Baking soda","notes":"","url":"http:\/\/makeprojects.com\/Item\/Baking_soda","thumbnail":""},{"text":"Baking powder","notes":"","url":"http:\/\/makeprojects.com\/Item\/Baking_powder","thumbnail":""}],"prereqs":[],"steps":[{"title":"Mix together the ingredients.","lines":[{"text":"In a medium bowl, mix together the four, baking soda, and baking powder.","text_raw":"In a medium bowl, mix together the four, baking soda, and baking powder.","bullet":"black","level":0},{"text":"In a large bowl, whip together the butter, Crisco, sugar, vanilla, and egg.","text_raw":"In a large bowl, whip together the butter, Crisco, sugar, vanilla, and egg.","bullet":"black","level":0},{"text":"Slowly add the flour mixture to the sugar and butter mix, until throughly mixed.","text_raw":"Slowly add the flour mixture to the sugar and butter mix, until throughly mixed.","bullet":"black","level":0},{"text":"Measure and add chocolate chips.","text_raw":"Measure and add chocolate chips.","bullet":"black","level":0}],"object":null,"images":[],"number":1},{"title":"Grease two baking sheets.","lines":[{"text":"Using a measuring spoon, make small 2 tbsp balls and place them on the baking sheet, leaving about three inches in between each cookie.","text_raw":"Using a measuring spoon, make small 2 tbsp balls and place them on the baking sheet, leaving about three inches in between each cookie.","bullet":"black","level":0},{"text":"Once one sheet is filled, put it in the oven and bake the cookies for 10-12 minutes.","text_raw":"Once one sheet is filled, put it in the oven and bake the cookies for 10-12 minutes.","bullet":"black","level":0}],"object":null,"images":[],"number":2},{"title":"","lines":[{"text":"Continue baking batches of cookies in the same fashion as the first, swapping sheets between batches.","text_raw":"Continue baking batches of cookies in the same fashion as the first, swapping sheets between batches.","bullet":"black","level":0},{"text":"Once all of the cookies are done, leave them out to cool for about 15 minutes.","text_raw":"Once all of the cookies are done, leave them out to cool for about 15 minutes.","bullet":"icon_note","level":0}],"object":null,"images":[],"number":3},{"title":"","lines":[{"text":"You're done!","text_raw":"You're done!","bullet":"black","level":0}],"object":null,"images":[],"number":4}],"subject":"","summary":"A recipe to make small, soft, and light chocolate chip cookies.","time_required":"1 to 2 hours","title":"The PERFECT Chocolate Chip Cookie","tools":[{"text":"2 Baking sheets","notes":"","url":"http:\/\/makeprojects.com\/Item\/2_Baking_sheets","thumbnail":""},{"text":"Assorted mixing bowls","notes":"","url":"http:\/\/makeprojects.com\/Item\/Assorted_mixing_bowls","thumbnail":""},{"text":"measuring cups and spoons","notes":"","url":"http:\/\/makeprojects.com\/Item\/measuring_cups_and_spoons","thumbnail":""}],"type":"project"},"guideid":"2462"}