{"device":"Design","url":"http:\/\/makeprojects.com\/Project\/Benty\/3348\/1","guide":{"author":{"text":"Jacke Batzler","userid":18159},"categories":["Design","Design"],"conclusion":"","difficulty":"Moderate","documents":[],"flags":[{"title":"User-Contributed Project","flagid":"GUIDE_USER_CONTRIBUTED","text":"This project guide is not managed by MAKE staff."}],"guideid":3348,"image":{"imageid":58505,"text":"http:\/\/guide-images.makeprojects.org\/igi\/rwaAyET1VHE5maRG"},"introduction":"","introduction_rendered":"","locale":"en","parts":[],"prereqs":[],"steps":[{"title":"","lines":[{"text":"Insert wisdom here.","text_raw":"Insert wisdom here.","bullet":"black","level":0}],"object":null,"images":[{"imageid":58503,"orderby":1,"text":"http:\/\/guide-images.makeprojects.org\/igi\/P2M2rXjMJxVEDpDl"}],"number":1},{"title":"","lines":[{"text":"Insert wisdom here.","text_raw":"Insert wisdom here.","bullet":"black","level":0}],"object":null,"images":[{"imageid":58507,"orderby":1,"text":"http:\/\/guide-images.makeprojects.org\/igi\/o1KrrfRRB4SejuKZ"}],"number":2}],"subject":"","summary":"www.youtube.com\/user\/ValidZone","time_required":null,"title":"Benty","tools":[],"type":"project"},"guideid":"3348"}