{"device":"Computers","url":"http:\/\/makeprojects.com\/Project\/CardboardNinja\/3362\/1","guide":{"author":{"text":"shaun","userid":18252},"categories":["Computers","Video Making"],"conclusion":"","difficulty":"Moderate","documents":[],"flags":[{"title":"User-Contributed Project","flagid":"GUIDE_USER_CONTRIBUTED","text":"This project guide is not managed by MAKE staff."}],"guideid":3362,"image":{"imageid":58755,"text":"http:\/\/guide-images.makeprojects.org\/igi\/kIbaD2CF66vMBvxe"},"introduction":"","introduction_rendered":"","locale":"en","parts":[],"prereqs":[],"steps":[{"title":"","lines":[{"text":"Insert wisdom here.","text_raw":"Insert wisdom here.","bullet":"black","level":0}],"object":null,"images":[{"imageid":58755,"orderby":1,"text":"http:\/\/guide-images.makeprojects.org\/igi\/kIbaD2CF66vMBvxe"}],"number":1}],"subject":"","summary":null,"time_required":null,"title":"CardboardNinja","tools":[],"type":"project"},"guideid":"3362"}