{"device":"Circuits","url":"http:\/\/makeprojects.com\/Project\/Altoids+Breadboard\/583\/1","guide":{"author":{"text":"Luc Goldstein","userid":3576},"categories":["Circuits"],"conclusion":"","difficulty":"Easy","documents":[],"flags":[{"title":"User-Contributed Project","flagid":"GUIDE_USER_CONTRIBUTED","text":"This project guide is not managed by MAKE staff."}],"guideid":583,"image":{"imageid":0,"text":"http:\/\/cacher.dozuki.net\/static\/images\/make\/guide\/NoImageMP_96x72.gif"},"introduction":"<p>this is very easy and cheap. (I'm 13 i payed for it all and made it all by my self)<\/p>","introduction_rendered":"<p>this is very easy and cheap. (I'm 13 i payed for it all and made it all by my self)<\/p><div class=\"tools\"><strong>Tools<\/strong><ul><li><a href=\"http:\/\/www.radioshack.com\/product\/index.jsp?productId=12621825\">Hot glue gun<\/a><\/li><\/ul><\/div>","locale":"en","parts":[],"prereqs":[],"steps":[{"title":"","lines":[{"text":"Stuff you need","text_raw":"Stuff you need","bullet":"black","level":0},{"text":"Altiods can","text_raw":"Altiods can","bullet":"black","level":1},{"text":"Half size bread board (can get from amazon, maker shed, and raidioshack)","text_raw":"Half size bread board (can get from amazon, maker shed, and raidioshack)","bullet":"black","level":1},{"text":"double AAA battery holder","text_raw":"double AAA battery holder","bullet":"black","level":1},{"text":"various wanted components, LEDs, resistors, capacitors, etc.","text_raw":"various wanted components, LEDs, resistors, capacitors, etc.","bullet":"black","level":1}],"object":null,"images":[],"number":1},{"title":"","lines":[{"text":"Take one of the power rails off the bread board and stick it on the inside of the lid of the breadboard.","text_raw":"Take one of the power rails off the bread board and stick it on the inside of the lid of the breadboard.","bullet":"black","level":0}],"object":null,"images":[],"number":2},{"title":"","lines":[{"text":"hot glue the battery pack in the center on the inside.","text_raw":"hot glue the battery pack in the center on the inside.","bullet":"black","level":0},{"text":"Put the positive and negative leads from the battery pack in the remaining power rail and put just enough hot glue to hold them in. ( this is so they don't touch and short out the battery.)","text_raw":"Put the positive and negative leads from the battery pack in the remaining power rail and put just enough hot glue to hold them in. ( this is so they don't touch and short out the battery.)","bullet":"black","level":0}],"object":null,"images":[],"number":3},{"title":"","lines":[{"text":"Now just add what ever components to the two spaces in the bottom.","text_raw":"Now just add what ever components to the two spaces in the bottom.","bullet":"black","level":0}],"object":null,"images":[],"number":4}],"subject":"","summary":"how to make a small electronics kit in an Altiods can.","time_required":"10-15 minutes ","title":"Altoids Breadboard","tools":[{"text":"Hot glue gun","notes":"","url":"http:\/\/www.radioshack.com\/product\/index.jsp?productId=12621825","thumbnail":""}],"type":"project"},"guideid":"583"}