{"device":"Photography","url":"http:\/\/makeprojects.com\/Project\/72+LED+Macro+Ring\/727\/1","guide":{"author":{"text":"rec","userid":4555},"categories":["Photography","Photography"],"conclusion":"","difficulty":"Moderate","documents":[],"flags":[{"title":"Unsatisfactory Images","flagid":"GUIDE_LOUSY_PICTURES","text":"This project guide has low-quality images. Pictures need to be either re-edited or re-taken."},{"title":"Missing Steps","flagid":"GUIDE_MISSING_STEPS","text":"This project guide is incomplete or missing critical steps."},{"title":"Unpublished","flagid":"GUIDE_PRIVATE","text":"This project guide will not appear in search results but can still be viewed by anyone!"},{"title":"User-Contributed Project","flagid":"GUIDE_USER_CONTRIBUTED","text":"This project guide is not managed by MAKE staff."}],"guideid":727,"image":{"imageid":12076,"text":"http:\/\/guide-images.makeprojects.org\/igi\/QrJjqnSkZCVOsLp2"},"introduction":"<p>72 led macro ring (72mm) with reverse EF mount adapter<\/p>\n\n<p>With step Up rings can be used on any type of lens (52mm to 72mm)<\/p>\n\n<p>Total current drain ~ 1.2Ah at 5-6V, (4xAA rechargeable battery or indoor use 6V DC adapter)<\/p>\n\n<p>It is very lightweight: macro ring 76gr, battery holder with 4x AA inside 152gr<\/p>\n\n<p>The circuit is designed to have two phases of light, full or half (only half of the LEDs light up)<\/p>\n\n<p>Range is 5-20cm, ideal for super macro<\/p>\n\n<p><a href=\"http:\/\/apcc.tk\/index.php\/photo-galery\/category\/18-ledring\" rel=\"nofollow\">Photo Galery<\/a><\/p>","introduction_rendered":"<p>72 led macro ring (72mm) with reverse EF mount adapter<\/p>\n\n<p>With step Up rings can be used on any type of lens (52mm to 72mm)<\/p>\n\n<p>Total current drain ~ 1.2Ah at 5-6V, (4xAA rechargeable battery or indoor use 6V DC adapter)<\/p>\n\n<p>It is very lightweight: macro ring 76gr, battery holder with 4x AA inside 152gr<\/p>\n\n<p>The circuit is designed to have two phases of light, full or half (only half of the LEDs light up)<\/p>\n\n<p>Range is 5-20cm, ideal for super macro<\/p>\n\n<p><a href=\"http:\/\/apcc.tk\/index.php\/photo-galery\/category\/18-ledring\" rel=\"nofollow\">Photo Galery<\/a><\/p>","locale":"en","parts":[],"prereqs":[],"steps":[{"title":"","lines":[{"text":"Insert wisdom here.","text_raw":"Insert wisdom here.","bullet":"black","level":0}],"object":null,"images":[{"imageid":12076,"orderby":1,"text":"http:\/\/guide-images.makeprojects.org\/igi\/QrJjqnSkZCVOsLp2"}],"number":1}],"subject":"","summary":"Make a 72-LED macro ring (72mm) with reverse EF mount adapter. www.apcc.tk","time_required":null,"title":"72 LED Macro Ring","tools":[],"type":"project"},"guideid":"727"}