{"device":"DIY Space","url":"http:\/\/makeprojects.com\/Project\/NASA+MAKE+Challenge+2011+Winner%3A+%22Bring+It+Back%22+Microgravity+Kit\/768\/1","guide":{"author":{"text":"Prashant Rao","userid":4743},"categories":["DIY Space","Science Projects"],"conclusion":"","difficulty":"Difficult","documents":[],"flags":[{"title":"User-Contributed Project","flagid":"GUIDE_USER_CONTRIBUTED","text":"This project guide is not managed by MAKE staff."}],"guideid":768,"image":{"imageid":16917,"text":"http:\/\/guide-images.makeprojects.org\/igi\/AvO1bHOBKbDUITAe"},"introduction":"<p><strong>&quot;Bring It Back&quot; Microgravity Kit by Prashant Rao &amp; Subra Sankaran <\/strong><\/p>\n\n<p>Prashant Rao, Ph.D., Principal Engineer, Barrios\/Jacobs\/<wbr \/>ESCG<\/p>\n\n<p>Subra Sankaran, Ph.D., Senior Thermal Specialist, MEIT\/Jacobs\/ESC<wbr \/>G<\/p>\n\n<p>at NASA JSC, 2224 Bay Area Blvd, Houston TX 77058<\/p>\n\n<p>Three experiments are described here (with suggestions for additional experiments) that use molten wax in different setups to demonstrate important principles of science and engineering. They can be performed using substantially the same equipment, making the kit quite versatile. The experiments demonstrate the dominance of surface tension and wetting effects in the absence of gravity, the lack of buoyancy and its implications, all frozen in wax. Other science concepts related to these experiments are simulated boiling, two-phase fluid flow behavior in micro-gravity, fluid flow and bubble movements induced by temperature gradients, diffusion, melting and freezing in the absence of buoyancy and natural convection, wake flow, and so on.<\/p>\n\n<p>For these experiment you will need a small airtight container four to five milliliters in volume. Ideally it should not have a very thick wall because we are going to heat the contents with an external heater and we want to heat it up fast but the walls should be thick enough to withstand the increase in pressure due to heating and due to the expansion of the wax when it melts (about 10%). You will need to experiment with different containers or make one with acrylic sheet. We like a container with internal dimensions of 2 cm x 2 cm x 1 cm. This is pretty small but we need to heat and cool the contents fairly rapidly. Instructions for making boxes using acrylic sheets are available on the internet. The acrylic sheets used for a box of this size should be about 0.08&quot; (1\/8 in) thick. The pressure load when the box is heated will be as much as a 1.1 kg (2.4 lb) weight on the 2 cm x 2 cm face.<\/p>","introduction_rendered":"<p><strong>&quot;Bring It Back&quot; Microgravity Kit by Prashant Rao &amp; Subra Sankaran <\/strong><\/p>\n\n<p>Prashant Rao, Ph.D., Principal Engineer, Barrios\/Jacobs\/<wbr \/>ESCG<\/p>\n\n<p>Subra Sankaran, Ph.D., Senior Thermal Specialist, MEIT\/Jacobs\/ESC<wbr \/>G<\/p>\n\n<p>at NASA JSC, 2224 Bay Area Blvd, Houston TX 77058<\/p>\n\n<p>Three experiments are described here (with suggestions for additional experiments) that use molten wax in different setups to demonstrate important principles of science and engineering. They can be performed using substantially the same equipment, making the kit quite versatile. The experiments demonstrate the dominance of surface tension and wetting effects in the absence of gravity, the lack of buoyancy and its implications, all frozen in wax. Other science concepts related to these experiments are simulated boiling, two-phase fluid flow behavior in micro-gravity, fluid flow and bubble movements induced by temperature gradients, diffusion, melting and freezing in the absence of buoyancy and natural convection, wake flow, and so on.<\/p>\n\n<p>For these experiment you will need a small airtight container four to five milliliters in volume. Ideally it should not have a very thick wall because we are going to heat the contents with an external heater and we want to heat it up fast but the walls should be thick enough to withstand the increase in pressure due to heating and due to the expansion of the wax when it melts (about 10%). You will need to experiment with different containers or make one with acrylic sheet. We like a container with internal dimensions of 2 cm x 2 cm x 1 cm. This is pretty small but we need to heat and cool the contents fairly rapidly. Instructions for making boxes using acrylic sheets are available on the internet. The acrylic sheets used for a box of this size should be about 0.08&quot; (1\/8 in) thick. The pressure load when the box is heated will be as much as a 1.1 kg (2.4 lb) weight on the 2 cm x 2 cm face.<\/p><div class=\"parts\"><strong>Relevant parts<\/strong><ul><li><a href=\"http:\/\/www.makershed.com\/ProductDetails.asp?ProductCode=MKSP4\">Arduino microcontroller<\/a><\/li><li><a href=\"http:\/\/www.adafruit.com\/index.php?main_page=product_info&amp;amp;products_id=81\">Adafruit Motor\/Stepper\/Servo shield<\/a><\/li><li><a href=\"http:\/\/makeprojects.com\/Item\/Minco_THERMOFOIL_HEATER\">Minco THERMOFOIL HEATER<\/a><\/li><li><a href=\"http:\/\/www.adafruit.com\/index.php?main_page=product_info&amp;amp;cPath=35&amp;amp;products_id=163\">Three-axis Accelerometer<\/a><\/li><li><a href=\"http:\/\/makeprojects.com\/Item\/Acrylic_sheet\">Acrylic sheet<\/a><\/li><li><a href=\"http:\/\/makeprojects.com\/Item\/Case_Fan_50x50x15_5_Volt_12_cfm\">Case Fan 50x50x15 5 Volt 12 cfm<\/a><\/li><li><a href=\"http:\/\/makeprojects.com\/Item\/NiMh_Batteries_2500_mAh_size_AA\">NiMh Batteries 2500 mAh size AA<\/a><\/li><li><a href=\"http:\/\/www.pololu.com\/catalog\/product\/1160\">battery holder for 2 AA batteries<\/a><\/li><li><a href=\"http:\/\/www.radioshack.com\/product\/index.jsp?productId=2062253\">Battery holder, 4xAA<\/a><\/li><li><a href=\"http:\/\/makeprojects.com\/Item\/Wax\">Wax<\/a><\/li><li><a href=\"http:\/\/makeprojects.com\/Item\/Steel_Balls_1-2_mm_diameter\">Steel Balls 1-2 mm diameter<\/a><\/li><li><a href=\"http:\/\/makeprojects.com\/Item\/Tiny_figurines_5-8_mm_tall\">Tiny figurines 5-8 mm tall<\/a><\/li><\/ul><\/div><div class=\"tools\"><strong>Tools<\/strong><ul><li><a href=\"http:\/\/makeprojects.com\/Item\/Hand_tools\">Hand tools<\/a><\/li><li><a href=\"http:\/\/www.radioshack.com\/product\/index.jsp?productId=4214667\">Multimeter<\/a><\/li><li><a href=\"http:\/\/makeprojects.com\/Item\/Plastic_cutting_tools\">Plastic cutting tools<\/a><\/li><li><a href=\"http:\/\/makeprojects.com\/Item\/Soldering_desoldering_tools\">Soldering\/desoldering tools<\/a><\/li><li><a href=\"http:\/\/makeprojects.com\/Item\/Thermometer\">Thermometer<\/a><\/li><li><a href=\"http:\/\/makeprojects.com\/Item\/Wire_stripper_crimper\">Wire stripper\/crimper<\/a><\/li><\/ul><\/div>","locale":"en","parts":[{"text":"Arduino microcontroller","notes":"","url":"http:\/\/www.makershed.com\/ProductDetails.asp?ProductCode=MKSP4","thumbnail":""},{"text":"Adafruit Motor\/Stepper\/Servo shield","notes":"You will need additional drivers to handle currents of about 1.5 amps\r\nA Relay shield is also an option. See: http:\/\/www.emartee.com\/product\/41980\/Arduino-Relay-Shield","url":"http:\/\/www.adafruit.com\/index.php?main_page=product_info&amp;products_id=81","thumbnail":""},{"text":"Minco THERMOFOIL HEATER","notes":"Size 0.75in x 0.75in (19mm x 19mm)","url":"http:\/\/makeprojects.com\/Item\/Minco_THERMOFOIL_HEATER","thumbnail":""},{"text":"Three-axis Accelerometer","notes":"","url":"http:\/\/www.adafruit.com\/index.php?main_page=product_info&amp;cPath=35&amp;products_id=163","thumbnail":""},{"text":"Acrylic sheet","notes":"12in x 12in piece is sufficient for several trials","url":"http:\/\/makeprojects.com\/Item\/Acrylic_sheet","thumbnail":""},{"text":"Case Fan 50x50x15 5 Volt 12 cfm","notes":"","url":"http:\/\/makeprojects.com\/Item\/Case_Fan_50x50x15_5_Volt_12_cfm","thumbnail":""},{"text":"NiMh Batteries 2500 mAh size AA","notes":"Batteries can be purchased from several sources.","url":"http:\/\/makeprojects.com\/Item\/NiMh_Batteries_2500_mAh_size_AA","thumbnail":""},{"text":"battery holder for 2 AA batteries","notes":"Batteries should be side by side to keep length short","url":"http:\/\/www.pololu.com\/catalog\/product\/1160","thumbnail":""},{"text":"Battery holder, 4xAA","notes":"","url":"http:\/\/www.radioshack.com\/product\/index.jsp?productId=2062253","thumbnail":""},{"text":"Wax","notes":"","url":"http:\/\/makeprojects.com\/Item\/Wax","thumbnail":""},{"text":"Steel Balls 1-2 mm diameter","notes":"","url":"http:\/\/makeprojects.com\/Item\/Steel_Balls_1-2_mm_diameter","thumbnail":""},{"text":"Tiny figurines 5-8 mm tall","notes":"","url":"http:\/\/makeprojects.com\/Item\/Tiny_figurines_5-8_mm_tall","thumbnail":""}],"prereqs":[],"steps":[{"title":"","lines":[{"text":"You will be creating three different experimental setups for use within a single 10x10x10cm CubeSat module.","text_raw":"You will be creating three different experimental setups for use within a single 10x10x10cm CubeSat module.","bullet":"black","level":0},{"text":"In terms of technological applications, the first is equivalent to studying the fuel location in a liquid propellant tank during space travel. The second is equivalent to studying boiling heat transfer (e.g., see picture from Merte's experiments in the ISS) in space, and the third brings in multiple effects of absence of gravity.","text_raw":"In terms of technological applications, the first is equivalent to studying the fuel location in a liquid propellant tank during space travel. The second is equivalent to studying boiling heat transfer (e.g., see picture from Merte's experiments in the ISS) in space, and the third brings in multiple effects of absence of gravity.","bullet":"black","level":1},{"text":"Some of the actual space flight experiments that are closely related these wax experiments are: zero boil off test, Liquid Acquisition Devices in fuel tanks, several boiling heat transfer experiments, thermocapillary migration of bubbles, studies of liquid bridges \/ electro hydro dynamics, corner flows, and isothermal dentritic growth experiment shown in the picture below.","text_raw":"Some of the actual space flight experiments that are closely related these wax experiments are: zero boil off test, Liquid Acquisition Devices in fuel tanks, several boiling heat transfer experiments, thermocapillary migration of bubbles, studies of liquid bridges \/ electro hydro dynamics, corner flows, and isothermal dentritic growth experiment shown in the picture below.","bullet":"black","level":1}],"object":null,"images":[{"imageid":16919,"orderby":1,"text":"http:\/\/guide-images.makeprojects.org\/igi\/3H16MPMcT4p12Lwg"}],"number":1},{"title":"","lines":[{"text":"Prepare the 2 cm x 2 cm box with one 2 cm x 2 cm face open. Instructions for making acrylic boxes are available on the internet with Youtube being a particularly rich source of tutorials.","text_raw":"Prepare the 2 cm x 2 cm box with one 2 cm x 2 cm face open. Instructions for making acrylic boxes are available on the internet with Youtube being a particularly rich source of tutorials.","bullet":"black","level":0}],"object":null,"images":[{"imageid":16262,"orderby":1,"text":"http:\/\/guide-images.makeprojects.org\/igi\/yEywLI2dxS2dNh3K"}],"number":2},{"title":"","lines":[{"text":"Pour about 1 gram of molten wax into the container. It will be more helpful to use colored wax because it will be easier to see.","text_raw":"Pour about 1 gram of molten wax into the container. It will be more helpful to use colored wax because it will be easier to see.","bullet":"black","level":0},{"text":"Seal the box immediately after pouring the wax when it is still hot. This may help create a negative pressure inside the box when it cools and help reduce the pressure load on the box when it is heated.","text_raw":"Seal the box immediately after pouring the wax when it is still hot. This may help create a negative pressure inside the box when it cools and help reduce the pressure load on the box when it is heated.","bullet":"black","level":0},{"text":"Note: The wax expands up to 10% in volume when it melts! The pressure rise in the box can be calculated to see if the box can withstand the increase in pressure.","text_raw":"Note: The wax expands up to 10% in volume when it melts! The pressure rise in the box can be calculated to see if the box can withstand the increase in pressure.","bullet":"icon_note","level":0}],"object":null,"images":[{"imageid":16654,"orderby":1,"text":"http:\/\/guide-images.makeprojects.org\/igi\/EIAlbifkHcfFJZYp"}],"number":3},{"title":"","lines":[{"text":"Mount the heaters on the two large faces using stretch tape or shrink band.","text_raw":"Mount the heaters on the two large faces using stretch tape or shrink band.","bullet":"black","level":0},{"text":"Depending on the microgravity time available, it is desirable to use a thinner box. Also, place the heaters on the opposite sides of the box to achieve uniform heating.","text_raw":"Depending on the microgravity time available, it is desirable to use a thinner box. Also, place the heaters on the opposite sides of the box to achieve uniform heating.","bullet":"black","level":0}],"object":null,"images":[{"imageid":16638,"orderby":1,"text":"http:\/\/guide-images.makeprojects.org\/igi\/F1RuPOb3guShMUph"}],"number":4},{"title":"","lines":[{"text":"Connect the heaters in parallel to a 6 volt DC power supply and run it until all the wax is melted. It might be easier to see if the wax is melted if you place the box on one of the smaller sides and watch the wax flow.","text_raw":"Connect the heaters in parallel to a 6 volt DC power supply and run it until all the wax is melted. It might be easier to see if the wax is melted if you place the box on one of the smaller sides and watch the wax flow.","bullet":"black","level":0},{"text":"Connect an Ammeter in series with one of the heaters to note the current draw. This will be helpful later in choosing a power source.","text_raw":"Connect an Ammeter in series with one of the heaters to note the current draw. This will be helpful later in choosing a power source.","bullet":"black","level":0},{"text":"Note the ambient temperature.","text_raw":"Note the ambient temperature.","bullet":"black","level":0},{"text":"Switch off the heaters once the wax is melted. Note the time taken to melt the wax.","text_raw":"Switch off the heaters once the wax is melted. Note the time taken to melt the wax.","bullet":"black","level":0},{"text":"Calculate the energy needed to heat the box and the wax to the desired state, and predict the time needed for the heaters to be powered on. You will need material properties like the specific heat of the wax and box material, latent heat of the wax and power output of the heaters. The actual time taken will be longer than this rough calculation because the efficiency of the system will be less than 100%. Study the effect of natural convection and radiation in this 1g calculation.","text_raw":"Calculate the energy needed to heat the box and the wax to the desired state, and predict the time needed for the heaters to be powered on. You will need material properties like the specific heat of the wax and box material, latent heat of the wax and power output of the heaters. The actual time taken will be longer than this rough calculation because the efficiency of the system will be less than 100%. Study the effect of natural convection and radiation in this 1g calculation.","bullet":"black","level":0}],"object":null,"images":[{"imageid":17214,"orderby":1,"text":"http:\/\/guide-images.makeprojects.org\/igi\/dWhFOwbvVwJWeSeu"},{"imageid":17222,"orderby":2,"text":"http:\/\/guide-images.makeprojects.org\/igi\/A2TFhMIrBrPyOwEy"}],"number":5},{"title":"","lines":[{"text":"Wait for the wax to solidify. You can tilt the box slightly to see if it flows or if there is distortion in the crust that forms on top. If there is distortion in the crust it indicates that it is thin and the wax could break and flow through if tilted far enough.","text_raw":"Wait for the wax to solidify. You can tilt the box slightly to see if it flows or if there is distortion in the crust that forms on top. If there is distortion in the crust it indicates that it is thin and the wax could break and flow through if tilted far enough.","bullet":"black","level":0},{"text":"Note the time taken for the wax to solidify. What we really want to know is \u2013 how long does it take for a thick crust to form that will hold the shape of the wax? The answer to this question will fall in a range which is sufficient for our purposes. (Remember that the heat transfer is going to be less efficient than this in microgravity without convective heat transfer inside and outside the box.)","text_raw":"Note the time taken for the wax to solidify. What we really want to know is \u2013 how long does it take for a thick crust to form that will hold the shape of the wax? The answer to this question will fall in a range which is sufficient for our purposes. (Remember that the heat transfer is going to be less efficient than this in microgravity without convective heat transfer inside and outside the box.)","bullet":"black","level":0},{"text":"Now you are ready to design the experimental setup for Experiment 1 to go to space. Next we will work on Experiment 2.","text_raw":"Now you are ready to design the experimental setup for Experiment 1 to go to space. Next we will work on Experiment 2.","bullet":"black","level":0}],"object":null,"images":[{"imageid":17223,"orderby":1,"text":"http:\/\/guide-images.makeprojects.org\/igi\/gGmKdMLnmILybNUB"}],"number":6},{"title":"","lines":[{"text":"Prepare the box as for Experiment 1.","text_raw":"Prepare the box as for Experiment 1.","bullet":"black","level":0},{"text":"You will need about 2.5 grams of clear wax for this experiment.","text_raw":"You will need about 2.5 grams of clear wax for this experiment.","bullet":"black","level":0},{"text":"Pour in about 1 gram of molten wax into the box and wait for it to cool.","text_raw":"Pour in about 1 gram of molten wax into the box and wait for it to cool.","bullet":"black","level":0}],"object":null,"images":[{"imageid":16662,"orderby":1,"text":"http:\/\/guide-images.makeprojects.org\/igi\/RImiMCUAwC3vEbRg"}],"number":7},{"title":"","lines":[{"text":"Pour in about 1 gram of molten wax into the box and wait for it to cool.","text_raw":"Pour in about 1 gram of molten wax into the box and wait for it to cool.","bullet":"black","level":0},{"text":"Now you will embed a pocket of Alka-Seltzer in the wax. Here is one way to do it. When the wax is still soft, scoop out a hemispherical depression in the center 4-5 mm in diameter.","text_raw":"Now you will embed a pocket of Alka-Seltzer in the wax. Here is one way to do it. When the wax is still soft, scoop out a hemispherical depression in the center 4-5 mm in diameter.","bullet":"black","level":0},{"text":"Put in a small amount of coarsely powered Alka-Seltzer into the depression.","text_raw":"Put in a small amount of coarsely powered Alka-Seltzer into the depression.","bullet":"black","level":0}],"object":null,"images":[{"imageid":16655,"orderby":1,"text":"http:\/\/guide-images.makeprojects.org\/igi\/d6IJtUCjRRJAeOEu"}],"number":8},{"title":"","lines":[{"text":"Pour a few drops of colored molten wax on a warmed metal surface. A shallow saucepan will do nicely. The pan should be warm enough to keep the wax soft but not warm enough to melt it.","text_raw":"Pour a few drops of colored molten wax on a warmed metal surface. A shallow saucepan will do nicely. The pan should be warm enough to keep the wax soft but not warm enough to melt it.","bullet":"black","level":0},{"text":"The drops will form a film on the saucepan surface. Its diameter should be about 1.5 times the diameter of the Alka-Seltzer cell. Peel or scrape it off once it is solid enough.","text_raw":"The drops will form a film on the saucepan surface. Its diameter should be about 1.5 times the diameter of the Alka-Seltzer cell. Peel or scrape it off once it is solid enough.","bullet":"black","level":0},{"text":"Cover the Alka-Seltzer cell with the film. Press it in place and rub it lightly with the back of a heated spoon for a second or two so that it fuses well into the wax base but does not melt and mix with the Alka-Seltzer. This calls for trial and error to adjust the pressure from the spoon and time. You have just put the fusible wax barrier in place.","text_raw":"Cover the Alka-Seltzer cell with the film. Press it in place and rub it lightly with the back of a heated spoon for a second or two so that it fuses well into the wax base but does not melt and mix with the Alka-Seltzer. This calls for trial and error to adjust the pressure from the spoon and time. You have just put the fusible wax barrier in place.","bullet":"black","level":0},{"text":"Be careful with the spoon. You don\u2019t want to melt the fusible wax barrier.","text_raw":"Be careful with the spoon. You don\u2019t want to melt the fusible wax barrier.","bullet":"icon_caution","level":0}],"object":null,"images":[{"imageid":16661,"orderby":1,"text":"http:\/\/guide-images.makeprojects.org\/igi\/SuSWBcksXGqT4WHC"}],"number":9},{"title":"","lines":[{"text":"Pour about 1 gram of the molten wax into the box. (Or, place a sheet\/block of wax over and gently melt and fuse with the previous layer).The temperature of the wax should be just at or slightly above the melting point so that is almost about to solidify. This is because you definitely do not want to melt the fusible wax barrier.","text_raw":"Pour about 1 gram of the molten wax into the box. (Or, place a sheet\/block of wax over and gently melt and fuse with the previous layer).The temperature of the wax should be just at or slightly above the melting point so that is almost about to solidify. This is because you definitely do not want to melt the fusible wax barrier.","bullet":"black","level":0},{"text":"Repeat \u2013 You do not want to melt the fusible wax barrier!","text_raw":"Repeat \u2013 You do not want to melt the fusible wax barrier!","bullet":"black","level":0}],"object":null,"images":[{"imageid":16660,"orderby":1,"text":"http:\/\/guide-images.makeprojects.org\/igi\/sA1wtPIQTYl3Nlhn"}],"number":10},{"title":"","lines":[{"text":"When the wax is still soft but solid, scoop out a depression right on top of the Alka-Seltzer cell about the same diameter and deep enough to reach the fusible wax barrier. This is where you will realize the utility of a colored barrier. You can tell when you\u2019ve reached it! This is the water cell.","text_raw":"When the wax is still soft but solid, scoop out a depression right on top of the Alka-Seltzer cell about the same diameter and deep enough to reach the fusible wax barrier. This is where you will realize the utility of a colored barrier. You can tell when you\u2019ve reached it! This is the water cell.","bullet":"black","level":0},{"text":"Fill the water cell with water so that the top of the meniscus is level with the top surface of the wax. It might be more interesting if you color the water with a couple of drops of food coloring.","text_raw":"Fill the water cell with water so that the top of the meniscus is level with the top surface of the wax. It might be more interesting if you color the water with a couple of drops of food coloring.","bullet":"black","level":0},{"text":"Cover the water cell with a clear wax film in a manner similar to the fusible wax barrier.","text_raw":"Cover the water cell with a clear wax film in a manner similar to the fusible wax barrier.","bullet":"black","level":0}],"object":null,"images":[{"imageid":16659,"orderby":1,"text":"http:\/\/guide-images.makeprojects.org\/igi\/JLMEIoh2GlqMSFNT"}],"number":11},{"title":"","lines":[{"text":"Cover the water cell with a clear wax film in a manner similar to the fusible wax barrier.","text_raw":"Cover the water cell with a clear wax film in a manner similar to the fusible wax barrier.","bullet":"black","level":0},{"text":"Melt the remaining wax and pour it into the box. Again, the temperature of this wax should be at about the melting point so that it doesn\u2019t melt the water barrier. At this point the container should be about 2\/3 to 3\/4 full, not more. You want to leave space for the wax to expand.","text_raw":"Melt the remaining wax and pour it into the box. Again, the temperature of this wax should be at about the melting point so that it doesn\u2019t melt the water barrier. At this point the container should be about 2\/3 to 3\/4 full, not more. You want to leave space for the wax to expand.","bullet":"black","level":0},{"text":"Seal the box immediately after pouring the last layer when the wax is still hot. This may help create a negative pressure inside the box when it cools and help reduce the pressure load on the box when it is heated.","text_raw":"Seal the box immediately after pouring the last layer when the wax is still hot. This may help create a negative pressure inside the box when it cools and help reduce the pressure load on the box when it is heated.","bullet":"black","level":0}],"object":null,"images":[{"imageid":16658,"orderby":1,"text":"http:\/\/guide-images.makeprojects.org\/igi\/2VAjkuOdQV2Q3VWY"}],"number":12},{"title":"","lines":[{"text":"Mount the heaters on the box to the two large faces of the box using stretch tape or shrink band.","text_raw":"Mount the heaters on the box to the two large faces of the box using stretch tape or shrink band.","bullet":"black","level":0}],"object":null,"images":[{"imageid":16657,"orderby":1,"text":"http:\/\/guide-images.makeprojects.org\/igi\/SljM42GYyvFsELjC"}],"number":13},{"title":"For the Ground Test:","lines":[{"text":"Note the ambient temperature.","text_raw":"Note the ambient temperature.","bullet":"black","level":0},{"text":"Attach the heaters in parallel to a 6-volt supply with a Ammeter in series with at least one of the heaters.","text_raw":"Attach the heaters in parallel to a 6-volt supply with a Ammeter in series with at least one of the heaters.","bullet":"black","level":0},{"text":"Place the box with side with the Alka-Seltzer face down.","text_raw":"Place the box with side with the Alka-Seltzer face down.","bullet":"black","level":0},{"text":"Run the heaters until the wax is melted. When the wax is melted, the fusible wax barrier should also melt, and since the molten wax cannot remain as a sheet, will allow the water and Alka-Seltzer to come into contact and react.","text_raw":"Run the heaters until the wax is melted. When the wax is melted, the fusible wax barrier should also melt, and since the molten wax cannot remain as a sheet, will allow the water and Alka-Seltzer to come into contact and react.","bullet":"black","level":0},{"text":"Note the time and switch off the heaters. Note the time taken for the wax to solidify. (Remember that the heat transfer is going to be less efficient and very different from this in 0-g without convective heat transfer inside and outside the box.)","text_raw":"Note the time and switch off the heaters. Note the time taken for the wax to solidify. (Remember that the heat transfer is going to be less efficient and very different from this in 0-g without convective heat transfer inside and outside the box.)","bullet":"black","level":0},{"text":"Now you are ready to design the experimental setup for Experiment 2 to go to space. Next we will work on Experiment 3.","text_raw":"Now you are ready to design the experimental setup for Experiment 2 to go to space. Next we will work on Experiment 3.","bullet":"black","level":0}],"object":null,"images":[{"imageid":16663,"orderby":1,"text":"http:\/\/guide-images.makeprojects.org\/igi\/jXMnD5W4gWtRvN3a"}],"number":14},{"title":"","lines":[{"text":"From here on is described the setup for Experiment 3","text_raw":"From here on is described the setup for Experiment 3","bullet":"black","level":0},{"text":"Prepare the acrylic box so that the only open face is one of the small sides. This is because you are going to stack the wax in layers.","text_raw":"Prepare the acrylic box so that the only open face is one of the small sides. This is because you are going to stack the wax in layers.","bullet":"black","level":0}],"object":null,"images":[{"imageid":17215,"orderby":1,"text":"http:\/\/guide-images.makeprojects.org\/igi\/cuFWGk3r5qZpQjtk"}],"number":15},{"title":"","lines":[{"text":"You will need wax of two or three colors for this experiment with a total weight of about 2.5 grams.","text_raw":"You will need wax of two or three colors for this experiment with a total weight of about 2.5 grams.","bullet":"black","level":0},{"text":"Pour the molten wax into the box in layers waiting for the previous layer to solidify each time. (Or, you can do this experiment by merely placing several layers of differently colored wax on top of each other, along with embedding other objects and bubbles appropriately.) Thinner layers are better than thick ones to better visualize the patterns that you should see after the experiment. However it will take longer to prepare the experiment.","text_raw":"Pour the molten wax into the box in layers waiting for the previous layer to solidify each time. (Or, you can do this experiment by merely placing several layers of differently colored wax on top of each other, along with embedding other objects and bubbles appropriately.) Thinner layers are better than thick ones to better visualize the patterns that you should see after the experiment. However it will take longer to prepare the experiment.","bullet":"black","level":0},{"text":"As you prepare the layers, embed small items of various densities in the wax. You can try small ball bearings, bubbles (use the method given for Experiment 2), tiny figurines, etc.","text_raw":"As you prepare the layers, embed small items of various densities in the wax. You can try small ball bearings, bubbles (use the method given for Experiment 2), tiny figurines, etc.","bullet":"black","level":0},{"text":"The box should be about 2\/3 to 3\/4 full when you are done.","text_raw":"The box should be about 2\/3 to 3\/4 full when you are done.","bullet":"black","level":0},{"text":"Seal the box immediately after pouring the last layer when the wax is still hot. This may help create a negative pressure inside the box when it cools and help reduce the pressure load on the box when it is heated.","text_raw":"Seal the box immediately after pouring the last layer when the wax is still hot. This may help create a negative pressure inside the box when it cools and help reduce the pressure load on the box when it is heated.","bullet":"black","level":0}],"object":null,"images":[{"imageid":16664,"orderby":1,"text":"http:\/\/guide-images.makeprojects.org\/igi\/OHAXBr1Z32x2swnN"}],"number":16},{"title":"","lines":[{"text":"Mount the heaters and orient the box, say, on one of the small sides so that the wax layers are horizontal. You could also experiment with a vertical orientation.","text_raw":"Mount the heaters and orient the box, say, on one of the small sides so that the wax layers are horizontal. You could also experiment with a vertical orientation.","bullet":"black","level":0}],"object":null,"images":[{"imageid":16666,"orderby":1,"text":"http:\/\/guide-images.makeprojects.org\/igi\/qSUUg4kjHgYsYcny"}],"number":17},{"title":"","lines":[{"text":"Run a ground test. Note the experimental parameters as for Experiments 1 and 2.","text_raw":"Run a ground test. Note the experimental parameters as for Experiments 1 and 2.","bullet":"black","level":0},{"text":"Remember that the heat transfer is going to be less efficient and the flow patterns will be very different from this in microgravity without buoyancy and convective heat transfer inside and outside the box.","text_raw":"Remember that the heat transfer is going to be less efficient and the flow patterns will be very different from this in microgravity without buoyancy and convective heat transfer inside and outside the box.","bullet":"black","level":0}],"object":null,"images":[{"imageid":16667,"orderby":1,"text":"http:\/\/guide-images.makeprojects.org\/igi\/W2EfGPj6RfvB5IVo"}],"number":18},{"title":"Preparing the Experiments for Microgravity","lines":[{"text":"You will need to use the Arduino or some other similar microcontroller for the experiment. A microcontroller is required to determine the correct time to switch on and switch off the heaters and to run the fan. It is also needed to run a camera and control the lighting if you should choose to add those optional items.","text_raw":"You will need to use the Arduino or some other similar microcontroller for the experiment. A microcontroller is required to determine the correct time to switch on and switch off the heaters and to run the fan. It is also needed to run a camera and control the lighting if you should choose to add those optional items.","bullet":"black","level":0},{"text":"You will also need the capability of switching currents of up to 1.5 Amps for each of the heaters and up to about 0.5 Amps for the cooling fan. The Arduino does not have the native capacity to control such large currents so you will need a power or motor shield or a relay shield in addition.","text_raw":"You will also need the capability of switching currents of up to 1.5 Amps for each of the heaters and up to about 0.5 Amps for the cooling fan. The Arduino does not have the native capacity to control such large currents so you will need a power or motor shield or a relay shield in addition.","bullet":"black","level":0},{"text":"For the power supply we suggest six NiMh batteries in AA size of good quality and high energy capacity connected in series. NiCad batteries could also be an option. Both NiMh and NiCad batteries can withstand a high current draw but the NiCad battery usually has a lower total capacity (usually measured in mAh or milli-Ampere hour).","text_raw":"For the power supply we suggest six NiMh batteries in AA size of good quality and high energy capacity connected in series. NiCad batteries could also be an option. Both NiMh and NiCad batteries can withstand a high current draw but the NiCad battery usually has a lower total capacity (usually measured in mAh or milli-Ampere hour).","bullet":"black","level":0},{"text":"Instructions for developing the circuitry for your experiment should be obtained elsewhere. There is a wealth of information available on the internet for using the Arduino microcontroller.","text_raw":"Instructions for developing the circuitry for your experiment should be obtained elsewhere. There is a wealth of information available on the internet for using the Arduino microcontroller.","bullet":"black","level":0}],"object":null,"images":[{"imageid":16641,"orderby":1,"text":"http:\/\/guide-images.makeprojects.org\/igi\/fAgvKIQIKDlLGvuO"}],"number":19},{"title":"Using the Flight Plan","lines":[{"text":"The flight plan is crucial to the experiment. The time spent in microgravity is very limited and the available time has to be budgeted very carefully.","text_raw":"The flight plan is crucial to the experiment. The time spent in microgravity is very limited and the available time has to be budgeted very carefully.","bullet":"black","level":0},{"text":"A three-axis accelerometer like the ADXL335 needs to be used to measure the magnitude of the total acceleration in all three directions.","text_raw":"A three-axis accelerometer like the ADXL335 needs to be used to measure the magnitude of the total acceleration in all three directions.","bullet":"black","level":0},{"text":"You will need to use your ground-based measurements to decide when the heaters should be turned on and off and when the fan should be run and for how long.","text_raw":"You will need to use your ground-based measurements to decide when the heaters should be turned on and off and when the fan should be run and for how long.","bullet":"black","level":0}],"object":null,"images":[{"imageid":17216,"orderby":1,"text":"http:\/\/guide-images.makeprojects.org\/igi\/a2VXHU1uIrfL6Gi3"},{"imageid":17225,"orderby":2,"text":"http:\/\/guide-images.makeprojects.org\/igi\/Ju5uTlsLPJZENDe6"}],"number":20}],"subject":"","summary":"Use molten wax in different setups to demonstrate important principles of science and engineering.","time_required":"40 to 100 hours","title":"NASA MAKE Challenge 2011 Winner: \"Bring It Back\" Microgravity Kit","tools":[{"text":"Hand tools","notes":"Usual suspects","url":"http:\/\/makeprojects.com\/Item\/Hand_tools","thumbnail":""},{"text":"Multimeter","notes":"","url":"http:\/\/www.radioshack.com\/product\/index.jsp?productId=4214667","thumbnail":""},{"text":"Plastic cutting tools","notes":"Tools needed depend on the procedure used to build the acrylic box","url":"http:\/\/makeprojects.com\/Item\/Plastic_cutting_tools","thumbnail":""},{"text":"Soldering\/desoldering tools","notes":"","url":"http:\/\/makeprojects.com\/Item\/Soldering_desoldering_tools","thumbnail":""},{"text":"Thermometer","notes":"","url":"http:\/\/makeprojects.com\/Item\/Thermometer","thumbnail":""},{"text":"Wire stripper\/crimper","notes":"","url":"http:\/\/makeprojects.com\/Item\/Wire_stripper_crimper","thumbnail":""}],"type":"project"},"guideid":"768"}