{"device":"Gadgets","url":"http:\/\/makeprojects.com\/Project\/The+Mouse+Glove\/894\/1","guide":{"author":{"text":"Johnny","userid":4240},"categories":["Gadgets","Wearables"],"conclusion":"","difficulty":"Moderate","documents":[],"flags":[{"title":"Unpublished","flagid":"GUIDE_PRIVATE","text":"This project guide will not appear in search results but can still be viewed by anyone!"},{"title":"User-Contributed Project","flagid":"GUIDE_USER_CONTRIBUTED","text":"This project guide is not managed by MAKE staff."}],"guideid":894,"image":{"imageid":0,"text":"http:\/\/cacher.dozuki.net\/static\/images\/make\/guide\/NoImageMP_96x72.gif"},"introduction":"<p>The Mouse Glove is a glove that has the circuit board and parts of a wireless computer mouse inside.  This will allow you to move your hand along any surface and use it as a mouse.  The Mouse Glove also has fully functioning left and right buttons that are attached to your first two fingers.  It is a very simple project that costs anywhere between $10 and $25 depending on how expensive your mouse is.  It is portable, lightweight, and very convenient if you travel.  It is also a great project if you'r just starting to learn how to mod household electronics.<\/p>","introduction_rendered":"<p>The Mouse Glove is a glove that has the circuit board and parts of a wireless computer mouse inside.  This will allow you to move your hand along any surface and use it as a mouse.  The Mouse Glove also has fully functioning left and right buttons that are attached to your first two fingers.  It is a very simple project that costs anywhere between $10 and $25 depending on how expensive your mouse is.  It is portable, lightweight, and very convenient if you travel.  It is also a great project if you'r just starting to learn how to mod household electronics.<\/p>","locale":"en","parts":[],"prereqs":[],"steps":[],"subject":"","summary":"This simple hack shows you how to turn a glove into a wireless mouse with fully functioning buttons and controls.","time_required":null,"title":"The Mouse Glove","tools":[],"type":"project"},"guideid":"894"}