{"device":"Arduino","url":"http:\/\/makeprojects.com\/Project\/Arduino+BrUNO%3A+%22Hello+World%22\/1123\/1","guide":{"author":{"text":"Bruno","userid":6209},"categories":["Arduino","Arduino"],"conclusion":"<p>This was a piece of cake! But a sweet piece of cake for wetting the appetite to do more!<\/p>","difficulty":"Easy","documents":[],"flags":[{"title":"Missing Steps","flagid":"GUIDE_MISSING_STEPS","text":"This project guide is incomplete or missing critical steps."},{"title":"Unpublished","flagid":"GUIDE_PRIVATE","text":"This project guide will not appear in search results but can still be viewed by anyone!"},{"title":"User-Contributed Project","flagid":"GUIDE_USER_CONTRIBUTED","text":"This project guide is not managed by MAKE staff."}],"guideid":1123,"image":{"imageid":21811,"text":"http:\/\/guide-images.makeprojects.org\/igi\/pueKE62hYaMv4NLc"},"introduction":"","introduction_rendered":"<div class=\"parts\"><strong>Relevant parts<\/strong><ul><li><a href=\"http:\/\/www.makershed.com\/ProductDetails.asp?ProductCode=MKSP4\">Arduino Uno<\/a><\/li><li><a href=\"http:\/\/www.radioshack.com\/product\/index.jsp?productId=2062554\">LED, Red<\/a><\/li><li><a href=\"http:\/\/www.radioshack.com\/product\/index.jsp?productId=2734155\">Small Breadboard<\/a><\/li><li><a href=\"http:\/\/www.radioshack.com\/product\/index.jsp?productId=2049742\">Wire<\/a><\/li><li><a href=\"http:\/\/makeprojects.com\/Item\/misc_resistors_buttons_lights\">misc resistors, buttons, lights<\/a><\/li><\/ul><\/div><div class=\"tools\"><strong>Tools<\/strong><ul><li><a href=\"http:\/\/makeprojects.com\/Item\/Computer_running_Windows_XP_Vista_or_Mac_OS_X\">Computer running Windows XP, Vista, or Mac OS X<\/a><\/li><li><a href=\"http:\/\/www.radioshack.com\/product\/index.jsp?productId=3932543\">Wire cutter\/stripper<\/a><\/li><\/ul><\/div>","locale":"en","parts":[{"text":"Arduino Uno","notes":"","url":"http:\/\/www.makershed.com\/ProductDetails.asp?ProductCode=MKSP4","thumbnail":""},{"text":"LED, Red","notes":"","url":"http:\/\/www.radioshack.com\/product\/index.jsp?productId=2062554","thumbnail":""},{"text":"Small Breadboard","notes":"","url":"http:\/\/www.radioshack.com\/product\/index.jsp?productId=2734155","thumbnail":""},{"text":"Wire","notes":"","url":"http:\/\/www.radioshack.com\/product\/index.jsp?productId=2049742","thumbnail":""},{"text":"misc resistors, buttons, lights","notes":"","url":"http:\/\/makeprojects.com\/Item\/misc_resistors_buttons_lights","thumbnail":""}],"prereqs":[],"steps":[{"title":"","lines":[{"text":"Insert wisdom here.","text_raw":"Insert wisdom here.","bullet":"black","level":0}],"object":null,"images":[{"imageid":21811,"orderby":1,"text":"http:\/\/guide-images.makeprojects.org\/igi\/pueKE62hYaMv4NLc"}],"number":1}],"subject":"","summary":"Just doing Hello World on Arduino","time_required":"15 mins","title":"Arduino BrUNO: \"Hello World\"","tools":[{"text":"Computer running Windows XP, Vista, or Mac OS X","notes":"","url":"http:\/\/makeprojects.com\/Item\/Computer_running_Windows_XP_Vista_or_Mac_OS_X","thumbnail":""},{"text":"Wire cutter\/stripper","notes":"","url":"http:\/\/www.radioshack.com\/product\/index.jsp?productId=3932543","thumbnail":""}],"type":"project"},"guideid":"1123"}