{"device":"Gaming","url":"http:\/\/makeprojects.com\/Project\/HoLyDoxx\/2483\/1","guide":{"author":{"text":"narkzc","userid":13682},"categories":["Gaming","Gaming"],"conclusion":"","difficulty":"Moderate","documents":[],"flags":[{"title":"User-Contributed Project","flagid":"GUIDE_USER_CONTRIBUTED","text":"This project guide is not managed by MAKE staff."}],"guideid":2483,"image":{"imageid":0,"text":"http:\/\/cacher.dozuki.net\/static\/images\/make\/guide\/NoImageMP_96x72.gif"},"introduction":"","introduction_rendered":"","locale":"en","parts":[],"prereqs":[],"steps":[],"subject":"","summary":"HoLyDoxx","time_required":null,"title":"HoLyDoxx","tools":[],"type":"project"},"guideid":"2483"}